main.py
iflow_mcp_windows_mcp-0.1.1.dist-info/licenses/LICENSE
src/__init__.py
src/desktop/__init__.py
src/desktop/config.py
src/desktop/views.py
src/tree/__init__.py
src/tree/config.py
src/tree/utils.py
src/tree/views.py
iflow_mcp_windows_mcp-0.1.1.dist-info/METADATA
iflow_mcp_windows_mcp-0.1.1.dist-info/WHEEL
iflow_mcp_windows_mcp-0.1.1.dist-info/entry_points.txt
iflow_mcp_windows_mcp-0.1.1.dist-info/top_level.txt
iflow_mcp_windows_mcp-0.1.1.dist-info/RECORD
