Metadata-Version: 2.4
Name: iflow-mcp_windows-mcp
Version: 0.1.1
Summary: Lightweight MCP Server for interacting with Windows Operating System.
Author-email: Jeomon George <jeogeoalukka@gmail.com>
License: MIT License
Project-URL: homepage, https://github.com/CursorTouch
Keywords: windows,mcp,ai,desktop,ai agent
Requires-Python: >=3.13
License-File: LICENSE
Requires-Dist: fastmcp>=2.8.1
Requires-Dist: fuzzywuzzy>=0.18.0
Requires-Dist: humancursor>=1.1.5
Requires-Dist: ipykernel>=6.30.0
Requires-Dist: live-inspect>=0.1.1
Requires-Dist: markdownify>=1.1.0
Requires-Dist: pillow>=11.2.1
Requires-Dist: psutil>=7.0.0
Requires-Dist: pyautogui>=0.9.54
Requires-Dist: pygetwindow>=0.0.9
Requires-Dist: python-levenshtein>=0.27.1
Requires-Dist: requests>=2.32.3
Requires-Dist: uiautomation>=2.0.24
Dynamic: license-file
